{"Players":[{"score":75,"name":"Alice"},{"score":42,"name":"Bob"},{"score":88,"name":"Charlie"},{"score":60,"name":"Diana"},{"score":90,"name":"Eve"},{"score":20,"name":"Frank"},{"score":50,"name":"Grace"},{"score":33,"name":"Hannah"},{"score":77,"name":"Isaac"},{"score":45,"name":"Jack"},{"_id":"jbnsk1:XD=7af1-371ec-1962b","age":21,"name":"Jebong"},{"name":"Jebong","age":21,"_id":"jbnsk1:XD=18b5-fc786-f005a"},{"_id":"jbnsk1:XD=d717-c6d8e-bed7c","age":21,"name":"Jebong"}],"Pokemon":[{"name":"Jebong","age":21,"_id":"jbnsk1:XD=9933-c7417-26793"},{"_id":"jbnsk1:XD=4d4f-2b507-af854","age":21,"name":"Nick"}]}